MANIFEST.in
README.md
requirements-c.txt
requirements-dev.txt
requirements.txt
setup.py
bc4py/__init__.py
bc4py/config.py
bc4py/exit.py
bc4py/gittool.py
bc4py/typing.py
bc4py/utils.py
bc4py.egg-info/PKG-INFO
bc4py.egg-info/SOURCES.txt
bc4py.egg-info/dependency_links.txt
bc4py.egg-info/requires.txt
bc4py.egg-info/top_level.txt
bc4py/bip32/__init__.py
bc4py/bip32/base58.py
bc4py/bip32/bip32.py
bc4py/bip32/utils.py
bc4py/chain/__init__.py
bc4py/chain/block.py
bc4py/chain/difficulty.py
bc4py/chain/genesisblock.py
bc4py/chain/msgpack.py
bc4py/chain/signature.py
bc4py/chain/tx.py
bc4py/chain/utils.py
bc4py/chain/workhash.py
bc4py/chain/checking/__init__.py
bc4py/chain/checking/checkblock.py
bc4py/chain/checking/checktx.py
bc4py/chain/checking/tx_mintcoin.py
bc4py/chain/checking/tx_reward.py
bc4py/chain/checking/utils.py
bc4py/database/__init__.py
bc4py/database/account.py
bc4py/database/builder.py
bc4py/database/create.py
bc4py/database/mintcoin.py
bc4py/database/tools.py
bc4py/for_debug/__init__.py
bc4py/user/__init__.py
bc4py/user/boot.py
bc4py/user/generate.py
bc4py/user/tools.py
bc4py/user/api/__init__.py
bc4py/user/api/accountinfo.py
bc4py/user/api/baseinfo.py
bc4py/user/api/chaininfo.py
bc4py/user/api/createtx.py
bc4py/user/api/editaccount.py
bc4py/user/api/server.py
bc4py/user/api/usertool.py
bc4py/user/api/utils.py
bc4py/user/api/websocket.py
bc4py/user/api/jsonrpc/__init__.py
bc4py/user/api/jsonrpc/account.py
bc4py/user/api/jsonrpc/mining.py
bc4py/user/api/jsonrpc/others.py
bc4py/user/api/static/8bitwallet.html
bc4py/user/api/static/doc_account.md
bc4py/user/api/static/doc_blockchain.md
bc4py/user/api/static/doc_others.md
bc4py/user/api/static/doc_sending.md
bc4py/user/api/static/doc_system.md
bc4py/user/api/static/favicon.ico
bc4py/user/api/static/index.md
bc4py/user/api/static/md_renderer.html
bc4py/user/api/static/sample.md
bc4py/user/api/static/test-response-rest.html
bc4py/user/api/static/test-response-ws.html
bc4py/user/api/static/image/python-min-x16.png
bc4py/user/api/static/image/python-min-x32.png
bc4py/user/api/static/image/python-min-x64.png
bc4py/user/api/static/js/8bitwallet.js
