Metadata-Version: 2.1
Name: bc4py
Version: 0.0.28a0
Summary: Simple blockchain library for python3.
Home-page: https://github.com/namuyan/bc4py
Author: namuyan
License: MIT Licence
Platform: UNKNOWN
Classifier: Programming Language :: Python :: 3.6
Classifier: License :: OSI Approved :: MIT License
